cerebrium_cli.py
cerebrium-2.2.0.dist-info/licenses/LICENSE
cerebrium-2.2.0.dist-info/METADATA
cerebrium-2.2.0.dist-info/WHEEL
cerebrium-2.2.0.dist-info/entry_points.txt
cerebrium-2.2.0.dist-info/top_level.txt
cerebrium-2.2.0.dist-info/RECORD
