Metadata-Version: 2.4
Name: cerebrium
Version: 2.2.0
Summary: CLI for deploying and managing Cerebrium apps
Author-email: Cerebrium AI <support@cerebrium.ai>
License: MIT
Project-URL: Documentation, https://docs.cerebrium.ai/
Project-URL: Repository, https://github.com/CerebriumAI/cerebrium
Project-URL: Issues, https://github.com/CerebriumAI/cerebrium/issues
Project-URL: Changelog, https://github.com/CerebriumAI/cerebrium/releases
Keywords: cerebrium,cli,deployment,ai,ml,machine-learning
Classifier: Development Status :: 5 - Production/Stable
Classifier: Intended Audience :: Developers
Classifier: License :: OSI Approved :: MIT License
Classifier: Programming Language :: Python :: 3
Classifier: Programming Language :: Python :: 3.8
Classifier: Programming Language :: Python :: 3.9
Classifier: Programming Language :: Python :: 3.10
Classifier: Programming Language :: Python :: 3.11
Classifier: Programming Language :: Python :: 3.12
Classifier: Programming Language :: Python :: 3.13
Classifier: Operating System :: POSIX :: Linux
Classifier: Operating System :: MacOS
Classifier: Operating System :: Microsoft :: Windows
Classifier: Topic :: Software Development :: Libraries :: Python Modules
Classifier: Topic :: System :: Systems Administration
Requires-Python: >=3.8
License-File: LICENSE
Dynamic: license-file
